CHANGES.txt
LICENSE.txt
MANIFEST.in
README.txt
bootstrap.py
buildout.cfg
setup.py
src/m01/__init__.py
src/m01.remote.egg-info/PKG-INFO
src/m01.remote.egg-info/SOURCES.txt
src/m01.remote.egg-info/dependency_links.txt
src/m01.remote.egg-info/namespace_packages.txt
src/m01.remote.egg-info/not-zip-safe
src/m01.remote.egg-info/requires.txt
src/m01.remote.egg-info/top_level.txt
src/m01/remote/README.txt
src/m01/remote/__init__.py
src/m01/remote/configure.zcml
src/m01/remote/exceptions.py
src/m01/remote/interfaces.py
src/m01/remote/job.py
src/m01/remote/job.zcml
src/m01/remote/layer.py
src/m01/remote/layer.zcml
src/m01/remote/processor.py
src/m01/remote/scheduler.py
src/m01/remote/scheduler.txt
src/m01/remote/scheduler.zcml
src/m01/remote/subscriber.py
src/m01/remote/subscriber.zcml
src/m01/remote/tests.py
src/m01/remote/traverser.py
src/m01/remote/traverser.zcml
src/m01/remote/vocabulary.py
src/m01/remote/vocabulary.zcml
src/m01/remote/worker.py
src/m01/remote/worker.txt
src/m01/remote/testing/__init__.py